odoo/addons/spec_driven_model/README.rst
odoo/addons/spec_driven_model/__init__.py
odoo/addons/spec_driven_model/__manifest__.py
odoo/addons/spec_driven_model/hooks.py
odoo/addons/spec_driven_model/i18n/pt_BR.po
odoo/addons/spec_driven_model/i18n/spec_driven_model.pot
odoo/addons/spec_driven_model/models/__init__.py
odoo/addons/spec_driven_model/models/spec_export.py
odoo/addons/spec_driven_model/models/spec_import.py
odoo/addons/spec_driven_model/models/spec_mixin.py
odoo/addons/spec_driven_model/models/spec_models.py
odoo/addons/spec_driven_model/models/spec_view.py
odoo/addons/spec_driven_model/readme/CONTRIBUTORS.rst
odoo/addons/spec_driven_model/static/description/icon.png
odoo/addons/spec_driven_model/tests/PurchaseOrderSchema.xsd
odoo/addons/spec_driven_model/tests/__init__.py
odoo/addons/spec_driven_model/tests/fake_mixin.py
odoo/addons/spec_driven_model/tests/fake_odoo_purchase.py
odoo/addons/spec_driven_model/tests/purchase_order_lib.py
odoo/addons/spec_driven_model/tests/spec_poxsd.py
odoo/addons/spec_driven_model/tests/spec_purchase.py
odoo/addons/spec_driven_model/tests/test_spec_model.py
odoo13_addon_spec_driven_model-13.0.1.0.1.dev3.dist-info/METADATA
odoo13_addon_spec_driven_model-13.0.1.0.1.dev3.dist-info/WHEEL
odoo13_addon_spec_driven_model-13.0.1.0.1.dev3.dist-info/top_level.txt
odoo13_addon_spec_driven_model-13.0.1.0.1.dev3.dist-info/RECORD
