Metadata-Version: 2.1
Name: odoo13-addon-spec-driven-model
Version: 13.0.1.0.1.dev3
Summary: Tools for specifications driven mixins (from xsd for instance)
Home-page: https://github.com/OCA/l10n-brazil
Author: Akretion,Odoo Community Association (OCA)
Author-email: support@odoo-community.org
License: LGPL-3
Platform: UNKNOWN
Classifier: Programming Language :: Python
Classifier: Framework :: Odoo
Classifier: Framework :: Odoo :: 13.0
Classifier: License :: OSI Approved :: GNU Lesser General Public License v3 (LGPLv3)
Classifier: Development Status :: 4 - Beta
Requires-Python: >=3.5
Requires-Dist: odoo <13.1dev,>=13.0a
Requires-Dist: odoo-test-helper
